homcloud/abstract_filtration.py
homcloud/alpha_filtration.py
homcloud/alpha_shape2_ext.cp313-win_amd64.pyd
homcloud/alpha_shape3_ext.cp313-win_amd64.pyd
homcloud/alpha_voronoi_relative_mask.py
homcloud/argparse_common.py
homcloud/bitmap.py
homcloud/build_phtrees.py
homcloud/cgal_info.cp313-win_amd64.pyd
homcloud/codebook.py
homcloud/coupled_alpha.py
homcloud/coupled_alpha_ext.cp313-win_amd64.pyd
homcloud/cubical_ext.cp313-win_amd64.pyd
homcloud/delegate.py
homcloud/dipha.py
homcloud/distance_transform_ext.cp313-win_amd64.pyd
homcloud/geometry_resolver.py
homcloud/graph_optimal_one_cycle.py
homcloud/hera_bottleneck.cp313-win_amd64.pyd
homcloud/hera_wasserstein.cp313-win_amd64.pyd
homcloud/histogram.py
homcloud/homccube.cp313-win_amd64.pyd
homcloud/int_reduction.py
homcloud/int_reduction_ext.cp313-win_amd64.pyd
homcloud/license.py
homcloud/maximal_0_component.py
homcloud/modp_reduction.py
homcloud/modp_reduction_ext.cp313-win_amd64.pyd
homcloud/norms_for_matplotlib.py
homcloud/numpyencoder.py
homcloud/optimal_one_cycle.py
homcloud/optimal_one_cycle_ext.cp313-win_amd64.pyd
homcloud/optvol.py
homcloud/pdgm.py
homcloud/pdgm_format.py
homcloud/periodic_alpha_shape2_ext.cp313-win_amd64.pyd
homcloud/periodic_alpha_shape3_ext.cp313-win_amd64.pyd
homcloud/ph_routine.py
homcloud/phat_ext.cp313-win_amd64.pyd
homcloud/phtrees.py
homcloud/pict_tree.cp313-win_amd64.pyd
homcloud/plot_PD.py
homcloud/plot_PD_slice.py
homcloud/plotly_3d.py
homcloud/py3dmolhelper.py
homcloud/pyvistahelper.py
homcloud/rips.py
homcloud/self_check.py
homcloud/show_pdgm_metadata.py
homcloud/simplicial_levelset.py
homcloud/spatial_searcher.py
homcloud/utils.py
homcloud/version.py
homcloud/cli/__init__.py
homcloud/cli/abstract_filtration.py
homcloud/cli/build_phtrees.py
homcloud/cli/dump_diagram.py
homcloud/cli/optvol.py
homcloud/cli/pc_alpha.py
homcloud/cli/phtrees.py
homcloud/cli/plot_PD.py
homcloud/cli/plot_PD_slice.py
homcloud/cli/rips.py
homcloud/cli/vectorize_PD.py
homcloud/cli/view_index_pict.py
homcloud-5.2.0.dist-info/licenses/LICENSE
homcloud-5.2.0.dist-info/METADATA
homcloud-5.2.0.dist-info/WHEEL
homcloud-5.2.0.dist-info/entry_points.txt
homcloud-5.2.0.dist-info/top_level.txt
homcloud-5.2.0.dist-info/RECORD
