Metadata-Version: 2.4
Name: homcloud
Version: 5.2.0
Summary: HomCloud, persistent homology based data analysis package
Author-email: Ippei Obayashi <i.obayashi@okayama-u.ac.jp>
License-Expression: GPL-3.0-or-later
Project-URL: homepage, http://homcloud.dev
Keywords: persistent homology
Classifier: Programming Language :: Python :: 3 :: Only
Classifier: Intended Audience :: Science/Research
Requires-Python: >=3.10
License-File: LICENSE
Requires-Dist: numpy
Requires-Dist: matplotlib
Requires-Dist: scipy
Requires-Dist: scikit-learn
Requires-Dist: msgpack
Requires-Dist: Pillow
Requires-Dist: pulp
Requires-Dist: imageio
Requires-Dist: Cython
Requires-Dist: ripser
Requires-Dist: cached-property
Requires-Dist: plotly
Requires-Dist: pyvista
Provides-Extra: unittest
Requires-Dist: pytest>=3.0; extra == "unittest"
Requires-Dist: pytest-mock; extra == "unittest"
Requires-Dist: pytest-qt; extra == "unittest"
Requires-Dist: pytest-xdist; extra == "unittest"
Provides-Extra: recommended
Requires-Dist: pyqt6; extra == "recommended"
Requires-Dist: pyvista[all]; extra == "recommended"
Requires-Dist: jupyter; extra == "recommended"
Requires-Dist: pyvistaqt; extra == "recommended"
Provides-Extra: recommended-torch
Requires-Dist: torch; extra == "recommended-torch"
Requires-Dist: torchvision; extra == "recommended-torch"
Requires-Dist: torchaudio; extra == "recommended-torch"
Dynamic: license-file
